setup.py
hmacauth/__init__.py
hmacauth/digest.py
hmacauth/client/__init__.py
hmacauth/client/authenticated_request.py
hmacauth/server/__init__.py
hmacauth/server/hmac_authorizer.py
tests/client/__init__.py
tests/client/test_authenticated_request.py
tests/server/__init__.py
tests/server/test_hmac_authorizer.py
ustudio_hmac_tornado.egg-info/PKG-INFO
ustudio_hmac_tornado.egg-info/SOURCES.txt
ustudio_hmac_tornado.egg-info/dependency_links.txt
ustudio_hmac_tornado.egg-info/requires.txt
ustudio_hmac_tornado.egg-info/top_level.txt