Metadata-Version: 1.0
Name: ustudio-hmac-tornado
Version: 0.2.0
Summary: Simple HMAC Client/Server authentication for Tornado
Home-page: https://github.com/ustudio/ustudio-hmac-tornado
Author: UNKNOWN
Author-email: UNKNOWN
License: UNKNOWN
Platform: UNKNOWN
